{"nodes": [{"id": "laravel_best_practices_skill_framework", "label": "Laravel Best Practices Framework", "file_type": "document", "source_file": ".agents/skills/laravel-best-practices/SKILL.md", "source_location": null, "source_url": null, "captured_at": null, "author": "laravel", "contributor": null, "rationale": "Provides prioritized Laravel defaults while requiring established project conventions to take precedence."}], "edges": [{"source": "laravel_best_practices_skill_framework", "target": "rules_db_performance_practices", "relation": "references", "confidence": "EXTRACTED", "confidence_score": 1.0, "source_file": ".agents/skills/laravel-best-practices/SKILL.md", "source_location": null, "weight": 1.0}, {"source": "laravel_best_practices_skill_framework", "target": "rules_advanced_queries_patterns", "relation": "references", "confidence": "EXTRACTED", "confidence_score": 1.0, "source_file": ".agents/skills/laravel-best-practices/SKILL.md", "source_location": null, "weight": 1.0}, {"source": "laravel_best_practices_skill_framework", "target": "rules_security_practices", "relation": "references", "confidence": "EXTRACTED", "confidence_score": 1.0, "source_file": ".agents/skills/laravel-best-practices/SKILL.md", "source_location": null, "weight": 1.0}, {"source": "laravel_best_practices_skill_framework", "target": "rules_caching_practices", "relation": "references", "confidence": "EXTRACTED", "confidence_score": 1.0, "source_file": ".agents/skills/laravel-best-practices/SKILL.md", "source_location": null, "weight": 1.0}, {"source": "laravel_best_practices_skill_framework", "target": "rules_eloquent_practices", "relation": "references", "confidence": "EXTRACTED", "confidence_score": 1.0, "source_file": ".agents/skills/laravel-best-practices/SKILL.md", "source_location": null, "weight": 1.0}, {"source": "laravel_best_practices_skill_framework", "target": "rules_validation_forms_practices", "relation": "references", "confidence": "EXTRACTED", "confidence_score": 1.0, "source_file": ".agents/skills/laravel-best-practices/SKILL.md", "source_location": null, "weight": 1.0}, {"source": "laravel_best_practices_skill_framework", "target": "rules_config_practices", "relation": "references", "confidence": "EXTRACTED", "confidence_score": 1.0, "source_file": ".agents/skills/laravel-best-practices/SKILL.md", "source_location": null, "weight": 1.0}, {"source": "laravel_best_practices_skill_framework", "target": "rules_testing_practices", "relation": "references", "confidence": "EXTRACTED", "confidence_score": 1.0, "source_file": ".agents/skills/laravel-best-practices/SKILL.md", "source_location": null, "weight": 1.0}, {"source": "laravel_best_practices_skill_framework", "target": "rules_queue_jobs_practices", "relation": "references", "confidence": "EXTRACTED", "confidence_score": 1.0, "source_file": ".agents/skills/laravel-best-practices/SKILL.md", "source_location": null, "weight": 1.0}, {"source": "laravel_best_practices_skill_framework", "target": "rules_routing_practices", "relation": "references", "confidence": "EXTRACTED", "confidence_score": 1.0, "source_file": ".agents/skills/laravel-best-practices/SKILL.md", "source_location": null, "weight": 1.0}, {"source": "laravel_best_practices_skill_framework", "target": "rules_http_client_practices", "relation": "references", "confidence": "EXTRACTED", "confidence_score": 1.0, "source_file": ".agents/skills/laravel-best-practices/SKILL.md", "source_location": null, "weight": 1.0}, {"source": "laravel_best_practices_skill_framework", "target": "rules_events_notifications_practices", "relation": "references", "confidence": "EXTRACTED", "confidence_score": 1.0, "source_file": ".agents/skills/laravel-best-practices/SKILL.md", "source_location": null, "weight": 1.0}, {"source": "laravel_best_practices_skill_framework", "target": "rules_mail_practices", "relation": "references", "confidence": "EXTRACTED", "confidence_score": 1.0, "source_file": ".agents/skills/laravel-best-practices/SKILL.md", "source_location": null, "weight": 1.0}, {"source": "laravel_best_practices_skill_framework", "target": "rules_error_handling_practices", "relation": "references", "confidence": "EXTRACTED", "confidence_score": 1.0, "source_file": ".agents/skills/laravel-best-practices/SKILL.md", "source_location": null, "weight": 1.0}, {"source": "laravel_best_practices_skill_framework", "target": "rules_scheduling_practices", "relation": "references", "confidence": "EXTRACTED", "confidence_score": 1.0, "source_file": ".agents/skills/laravel-best-practices/SKILL.md", "source_location": null, "weight": 1.0}, {"source": "laravel_best_practices_skill_framework", "target": "rules_architecture_practices", "relation": "references", "confidence": "EXTRACTED", "confidence_score": 1.0, "source_file": ".agents/skills/laravel-best-practices/SKILL.md", "source_location": null, "weight": 1.0}, {"source": "laravel_best_practices_skill_framework", "target": "rules_migrations_practices", "relation": "references", "confidence": "EXTRACTED", "confidence_score": 1.0, "source_file": ".agents/skills/laravel-best-practices/SKILL.md", "source_location": null, "weight": 1.0}, {"source": "laravel_best_practices_skill_framework", "target": "rules_collections_practices", "relation": "references", "confidence": "EXTRACTED", "confidence_score": 1.0, "source_file": ".agents/skills/laravel-best-practices/SKILL.md", "source_location": null, "weight": 1.0}, {"source": "laravel_best_practices_skill_framework", "target": "rules_blade_views_practices", "relation": "references", "confidence": "EXTRACTED", "confidence_score": 1.0, "source_file": ".agents/skills/laravel-best-practices/SKILL.md", "source_location": null, "weight": 1.0}, {"source": "laravel_best_practices_skill_framework", "target": "rules_style_conventions", "relation": "references", "confidence": "EXTRACTED", "confidence_score": 1.0, "source_file": ".agents/skills/laravel-best-practices/SKILL.md", "source_location": null, "weight": 1.0}], "hyperedges": []}